{
  "centrality": 0.55,
  "strength": 0.35,
  "correctness": 0.5,
  "clarity": 0.75,
  "dead_weight": 0.1,
  "single_issue": 1.0,
  "overall": 0.3,
  "reasoning": "The critique targets Section 3.3's treatment of threats, which is relevant to the paper's optimism about 'partial AM-convergence plus trade' scenarios. However, this is only one of several pathways the paper considers for reaching mostly-great futures (alongside WAM-convergence, compromise, etc.), so centrality is moderate rather than high. The critique makes a game-theoretic argument that non-threatening actors reveal exploitable information, but this argument has significant weaknesses: (1) the paper already acknowledges threats could 'eat into' most value and explicitly states optimism is 'uncertain' in unbounded/linear cases; (2) the claim that threatening actors have 'no incentive' to agree to legal systems ignores that even threatening actors benefit from predictable enforcement and avoiding mutual destruction; (3) the equilibrium analysis is asserted rather than demonstrated - in practice, reputation effects, coalitions of non-threatening actors, and coordination mechanisms could substantially mitigate the exploitation problem. The paper's acknowledgment that 'even small risks of executed threats can easily eat into the expected value' suggests the critique's concern is already 'priced in' to some degree. The critique is clear and focused on a single coherent issue, with minimal dead weight, but its correctness is undermined by overstating its case and ignoring countervailing considerations the position could deploy."
}